<aff xmlns:mml="http://www.w3.org/1998/Math/MathML" xmlns:xlink="http://www.w3.org/1999/xlink" id="hsr271167-aff-0007">
<label>
<sup>7</sup>
</label>
<named-content content-type="organisation-division">Assistant Professor of Medical Informatics. Non&#8208;Communicable Diseases Research Center, Sabzevar University of Medical Sciences, Sabzevar, Iran.</named-content>
<institution>Sabzevar University of Medical Sciences</institution>
<city>Sabzevar</city>
<country country="IR">Iran</country>
</aff>