<ref xmlns:mml="http://www.w3.org/1998/Math/MathML" xmlns:xlink="http://www.w3.org/1999/xlink" id="hsr271167-bib-0012"><label>12</label><mixed-citation publication-type="book" id="hsr271167-cit-0012">
<person-group person-group-type="editor">
<string-name>
<given-names>Y.&#8208;L.</given-names>
<surname>Cheng</surname>
</string-name>
</person-group>, <person-group person-group-type="editor">
<string-name>
<given-names>Y.&#8208;R.</given-names>
<surname>Wu</surname>
</string-name>
</person-group>, <person-group person-group-type="editor">
<string-name>
<given-names>K.&#8208;D.</given-names>
<surname>Lin</surname>
</string-name>
</person-group>, <person-group person-group-type="editor">
<string-name>
<given-names>C.&#8208;H. R.</given-names>
<surname>Lin</surname>
</string-name>
</person-group>, and <person-group person-group-type="editor">
<string-name>
<given-names>I.&#8208;M.</given-names>
<surname>Lin</surname>
</string-name>
</person-group>, ed., <part-title>Using Machine Learning for the Risk Factors Classification of Glycemic Control in Type 2 Diabetes Mellitus</part-title>.&#8221; in <source>Healthcare</source>. <publisher-name>MDPI</publisher-name>, <year>2023</year>).</mixed-citation></ref>